pyactuary.cpython-39-darwin.so
pyactuary-0.0.1.dist-info/LICENSE
pyactuary-0.0.1.dist-info/METADATA
pyactuary-0.0.1.dist-info/WHEEL
pyactuary-0.0.1.dist-info/top_level.txt
pyactuary-0.0.1.dist-info/RECORD
